pyngsild/__init__.py
pyngsild/agent/__init__.py
pyngsild/agent/bg/__init__.py
pyngsild/agent/bg/http_rest.py
pyngsild/agent/bg/http_upload.py
pyngsild/agent/bg/mqtt.py
pyngsild/agent/bg/scheduler.py
pyngsild/agent/bg/udp.py
pyngsild/agent/bg/watchdog.py
pyngsild/agent/processor.py
pyngsild/agent/stats.py
pyngsild/constants.py
pyngsild/ftpclient.py
pyngsild/sink/__init__.py
pyngsild/sink/ngsi.py
pyngsild/source/__init__.py
pyngsild/source/moresources.py
pyngsild/source/sourceftp.py
pyngsild/source/sourcemqtt.py
pyngsild/utils/__init__.py
pyngsild/utils/mqttclient.py
pyngsild/utils/stream.py
pyngsild-0.1.2.dist-info/LICENSE.txt
pyngsild-0.1.2.dist-info/WHEEL
pyngsild-0.1.2.dist-info/METADATA
pyngsild-0.1.2.dist-info/RECORD
