Metadata-Version: 2.1
Name: pyngsild
Version: 0.1.2
Summary: A Python data-centric framework whose goal is to ease and speed up the development of NGSI-LD agents
Home-page: https://github.com/Orange-OpenSource/pyngsild
License: Apache 2.0
Keywords: Fiware,NGSI,NGSI-LD,NGSI Agent
Author: fbattello
Author-email: fabien.battello@orange.com
Requires-Python: >=3.10,<4.0
Classifier: License :: Other/Proprietary License
Classifier: Programming Language :: Python :: 3
Classifier: Programming Language :: Python :: 3.10
Classifier: Topic :: Software Development :: Libraries :: Application Frameworks
Requires-Dist: fastapi (>=0.70.0,<0.71.0)
Requires-Dist: more-itertools (>=8.10.0,<9.0.0)
Requires-Dist: ngsildclient (>=0.1.3,<0.2.0)
Requires-Dist: openpyxl (>=3.0.9,<4.0.0)
Requires-Dist: paho-mqtt (>=1.6.1,<2.0.0)
Requires-Dist: pandas (>=1.3.4,<2.0.0)
Requires-Dist: python-multipart (>=0.0.5,<0.0.6)
Requires-Dist: schedule (>=1.1.0,<2.0.0)
Requires-Dist: shortuuid (>=1.0.8,<2.0.0)
Requires-Dist: uvicorn[standard] (>=0.15.0,<0.16.0)
Requires-Dist: watchgod (>=0.7,<0.8)
Requires-Dist: xmltodict (>=0.12.0,<0.13.0)
